firstapicalculator/__init__.py
firstapicalculator/api_helper.py
firstapicalculator/configuration.py
firstapicalculator/decorators.py
firstapicalculator/firstapicalculator_client.py
firstapicalculator/controllers/__init__.py
firstapicalculator/controllers/base_controller.py
firstapicalculator/controllers/simple_calculator_controller.py
firstapicalculator/exceptions/__init__.py
firstapicalculator/exceptions/api_exception.py
firstapicalculator/http/__init__.py
firstapicalculator/http/http_call_back.py
firstapicalculator/http/http_client.py
firstapicalculator/http/http_method_enum.py
firstapicalculator/http/http_request.py
firstapicalculator/http/http_response.py
firstapicalculator/http/requests_client.py
firstapicalculator/models/__init__.py
firstapicalculator/models/operation_type_enum.py
firstapicalculator/utilities/__init__.py
firstapicalculator/utilities/file_wrapper.py
tests/__init__.py
tests/http_response_catcher.py
tests/test_helper.py
tests/controllers/__init__.py
tests/controllers/controller_test_base.py
tests/controllers/test_simple_calculator_controller.py
calc_api_hs-1.0.dist-info/LICENSE
calc_api_hs-1.0.dist-info/METADATA
calc_api_hs-1.0.dist-info/WHEEL
calc_api_hs-1.0.dist-info/top_level.txt
calc_api_hs-1.0.dist-info/RECORD
